textIntegrityInspector/__init__.py
textIntegrityInspector/__main__.py
textIntegrityInspector/languageData.py
textIntegrityInspector/validator.py
textIntegrityInspector-0.1.5.dist-info/AUTHORS
textIntegrityInspector-0.1.5.dist-info/LICENSE
textIntegrityInspector-0.1.5.dist-info/METADATA
textIntegrityInspector-0.1.5.dist-info/WHEEL
textIntegrityInspector-0.1.5.dist-info/entry_points.txt
textIntegrityInspector-0.1.5.dist-info/pbr.json
textIntegrityInspector-0.1.5.dist-info/top_level.txt
textIntegrityInspector-0.1.5.dist-info/RECORD
