Metadata-Version: 2.1
Name: textIntegrityInspector
Version: 0.1.5
Summary: Valide the integrity of UTF-8 text files based on language-specific character sets.
Home-page: https://github.com/gschnellOnera/textIntegrityInspector
Author: Gaetan Schneller
License: MIT
Project-URL: Bug Tracker, https://github.com/gschnellOnera/textIntegrityInspector/issues
Project-URL: Documentation, https://github.com/gschnellOnera/textIntegrityInspector
Project-URL: Source Code, https://github.com/gschnellOnera/textIntegrityInspector
Classifier: Intended Audience :: Developers
Classifier: Intended Audience :: Information Technology
Classifier: Operating System :: OS Independent
Classifier: Programming Language :: Python
Classifier: Programming Language :: Python :: 3.8
Requires-Python: >=3.8
License-File: LICENSE
License-File: AUTHORS
